.gitlab-ci.yml
LICENSE
MANIFEST.in
README.md
install.ps1
install.sh
mkdocs.yml
pyproject.toml
requirements.txt
resources.qrc
setup.cfg
setup.py
data/icon.png
data/splash.png
data/tray_icon.png
iocbio.sparks.egg-info/PKG-INFO
iocbio.sparks.egg-info/SOURCES.txt
iocbio.sparks.egg-info/dependency_links.txt
iocbio.sparks.egg-info/entry_points.txt
iocbio.sparks.egg-info/requires.txt
iocbio.sparks.egg-info/top_level.txt
iocbio/sparks/__init__.py
iocbio/sparks/constants.py
iocbio/sparks/info.py
iocbio/sparks/worker.py
iocbio/sparks/app/__init__.py
iocbio/sparks/app/gui.py
iocbio/sparks/app/synthetic_data.py
iocbio/sparks/calc/__init__.py
iocbio/sparks/calc/auto_detect.py
iocbio/sparks/calc/spark.py
iocbio/sparks/calc/synthetic.py
iocbio/sparks/gui/__init__.py
iocbio/sparks/gui/custom_widgets.py
iocbio/sparks/gui/experiment_browser.py
iocbio/sparks/gui/experiment_plot.py
iocbio/sparks/gui/histogram_plot.py
iocbio/sparks/gui/import_image.py
iocbio/sparks/gui/lut.py
iocbio/sparks/gui/mainwindow.py
iocbio/sparks/gui/overview_plot.py
iocbio/sparks/gui/resources.py
iocbio/sparks/gui/spark_plot.py
iocbio/sparks/handler/__init__.py
iocbio/sparks/handler/experiment.py
iocbio/sparks/handler/image.py
iocbio/sparks/handler/roi.py
iocbio/sparks/io/__init__.py
iocbio/sparks/io/db.py
iocbio/sparks/io/export.py
iocbio/sparks/io/hash.py