Metadata-Version: 2.1
Name: iocbio.sparks
Version: 1.6.0
Summary: IOCBio Sparks: Semi-automatic calcium sparks detection software
Home-page: https://gitlab.com/iocbio/sparks
Author: IOCBio team
Author-email: iocbio@sysbio.ioc.ee
License: GPLv3
Classifier: Development Status :: 5 - Production/Stable
Classifier: Environment :: X11 Applications :: Qt
Classifier: Intended Audience :: Science/Research
Classifier: License :: OSI Approved :: GNU General Public License v3 or later (GPLv3+)
Classifier: Programming Language :: Python :: 3
Classifier: Topic :: Scientific/Engineering
License-File: LICENSE
